business.s.HTML
venue.S.HTML
body_scan/__init__.py
body_scan/_book/book.r.html
body_scan/_license/license.s.HTML
body_scan/_license/list/gpl-3.0-standalone.html
body_scan/_license/list/lentils license.s.HTML
body_scan/aggregate/__init__.py
body_scan/body_scan
body_scan/body_scan.s.HTML
body_scan/db/__init__.py
body_scan/functions/alarm_printer/__init__.py
body_scan/functions/exceptions.py
body_scan/functions/start/one.py
body_scan/functions/start/sequentially.py
body_scan/functions/start/simultaneously.py
body_scan/processes/collect/collect.s.HTML
body_scan/processes/collect/path.py
body_scan/processes/collect/start.proc.py
body_scan/processes/scan/process/keg/__init__.py
body_scan/processes/scan/process/keg/check.py
body_scan/processes/scan/process/scan.process.py
body_scan/processes/scan/scan.r.html
body_scan/processes/scan/starter/__init__.py
body_scan/processes/scan/starter/ask/__init__.py
body_scan/processes/scan/starter/keg/__init__.py
body_scan/processes/scan/starter/path.py
body_scan-1.1.0.dist-info/METADATA
body_scan-1.1.0.dist-info/WHEEL
body_scan-1.1.0.dist-info/entry_points.txt
body_scan-1.1.0.dist-info/RECORD
