Metadata-Version: 2.1
Name: body_scan
Version: 1.1.0
Summary: Health Checks
License: GPL-3.0-only
Requires-Python: >=3.10,<4.0
Classifier: License :: OSI Approved :: GNU General Public License v3 (GPLv3)
Classifier: Programming Language :: Python :: 3
Classifier: Programming Language :: Python :: 3.10
Classifier: Programming Language :: Python :: 3.11
Classifier: Programming Language :: Python :: 3.12
Requires-Dist: botanist (>=1.0.0,<2.0.0)
Requires-Dist: click (>=8.1.7,<9.0.0)
Requires-Dist: flask (>=3.0.3,<4.0.0)
Requires-Dist: pdoc3 (>=0.10.0,<0.11.0)
Requires-Dist: requests (>=2.31.0,<3.0.0)
Requires-Dist: textual (>=0.56.4,<0.57.0)
Requires-Dist: tinydb (>=4.8.0,<5.0.0)
Project-URL: GitLab, https://gitlab.com/reptilian_climates/body_scan.git
